{
    "additions":
    [
        {
            "type": "item-ground",
            "id": "RE402",
            "position": { "x": 233, "y": 29 }
        }
    ],
    "deletions":
    [
        {
            "scene": "decoration",
            "path": "MIDDLEGROUND/AfterPlayer/WallClimb/{0}"
        },
        {
            "scene": "decoration",
            "path": "MIDDLEGROUND/AfterPlayer/WallClimb/{1}"
        },
        {
            "scene": "layout",
            "path": "NAVIGATION/NAV_Wall Climb (1x3) (2)"
        }
    ]
}